[
  {
    "url": "https://tldv.io/post-sitemap.xml",
    "competitor": "tldv",
    "page": "post-sitemap.xml",
    "score": 0
  },
  {
    "url": "https://tldv.io/page-sitemap.xml",
    "competitor": "tldv",
    "page": "page-sitemap.xml",
    "score": 0
  },
  {
    "url": "https://tldv.io/category-sitemap.xml",
    "competitor": "tldv",
    "page": "category-sitemap.xml",
    "score": 0
  },
  {
    "url": "https://tldv.io/author-sitemap.xml",
    "competitor": "tldv",
    "page": "author-sitemap.xml",
    "score": 0
  },
  {
    "url": "https://tldv.io/settings",
    "competitor": "tldv",
    "page": "settings",
    "score": 0
  },
  {
    "url": "https://tldv.io/settings/profile",
    "competitor": "tldv",
    "page": "profile",
    "score": 0
  },
  {
    "url": "https://tldv.io/settings/billing",
    "competitor": "tldv",
    "page": "billing",
    "score": 0
  },
  {
    "url": "https://tldv.io/settings/workspace",
    "competitor": "tldv",
    "page": "workspace",
    "score": 0
  },
  {
    "url": "https://tldv.io/settings/team",
    "competitor": "tldv",
    "page": "team",
    "score": 0
  },
  {
    "url": "https://tldv.io/dashboard",
    "competitor": "tldv",
    "page": "dashboard",
    "score": 0
  },
  {
    "url": "https://tldv.io/projects",
    "competitor": "tldv",
    "page": "projects",
    "score": 0
  },
  {
    "url": "https://tldv.io/members",
    "competitor": "tldv",
    "page": "members",
    "score": 0
  },
  {
    "url": "https://tldv.io/billing",
    "competitor": "tldv",
    "page": "billing",
    "score": 0
  },
  {
    "url": "https://tldv.io/profile",
    "competitor": "tldv",
    "page": "profile",
    "score": 0
  },
  {
    "url": "https://tldv.io/account",
    "competitor": "tldv",
    "page": "account",
    "score": 0
  },
  {
    "url": "https://tldv.io/organization",
    "competitor": "tldv",
    "page": "organization",
    "score": 0
  },
  {
    "url": "https://tldv.io/notifications",
    "competitor": "tldv",
    "page": "notifications",
    "score": 0
  }
]
