[
  {
    "url": "https://tmetric.com/settings",
    "competitor": "tmetric",
    "page": "settings",
    "score": 0
  },
  {
    "url": "https://tmetric.com/settings/profile",
    "competitor": "tmetric",
    "page": "profile",
    "score": 0
  },
  {
    "url": "https://tmetric.com/settings/billing",
    "competitor": "tmetric",
    "page": "billing",
    "score": 0
  },
  {
    "url": "https://tmetric.com/settings/workspace",
    "competitor": "tmetric",
    "page": "workspace",
    "score": 0
  },
  {
    "url": "https://tmetric.com/settings/team",
    "competitor": "tmetric",
    "page": "team",
    "score": 0
  },
  {
    "url": "https://tmetric.com/dashboard",
    "competitor": "tmetric",
    "page": "dashboard",
    "score": 0
  },
  {
    "url": "https://tmetric.com/projects",
    "competitor": "tmetric",
    "page": "projects",
    "score": 0
  },
  {
    "url": "https://tmetric.com/members",
    "competitor": "tmetric",
    "page": "members",
    "score": 0
  },
  {
    "url": "https://tmetric.com/billing",
    "competitor": "tmetric",
    "page": "billing",
    "score": 0
  },
  {
    "url": "https://tmetric.com/profile",
    "competitor": "tmetric",
    "page": "profile",
    "score": 0
  },
  {
    "url": "https://tmetric.com/account",
    "competitor": "tmetric",
    "page": "account",
    "score": 0
  },
  {
    "url": "https://tmetric.com/organization",
    "competitor": "tmetric",
    "page": "organization",
    "score": 0
  },
  {
    "url": "https://tmetric.com/notifications",
    "competitor": "tmetric",
    "page": "notifications",
    "score": 0
  }
]
